python_freeipa/__init__.py
python_freeipa/client.py
python_freeipa/client_legacy.py
python_freeipa/client_meta.py
python_freeipa/exceptions.py
python_freeipa-1.0.10.dist-info/METADATA
python_freeipa-1.0.10.dist-info/WHEEL
python_freeipa-1.0.10.dist-info/licenses/LICENSE.md
python_freeipa-1.0.10.dist-info/RECORD
